google-flask-oauth/__init__.py
google-flask-oauth/_auth.py
google-flask-oauth/_aws_bootstrap.py
google-flask-oauth/_defaults.py
google-flask-oauth/oauth.py
google_flask_oauth/__init__.py
google_flask_oauth/_auth.py
google_flask_oauth/_aws_bootstrap.py
google_flask_oauth/_defaults.py
google_flask_oauth/decorators.py
google_flask_oauth/google_oauth.py
google_flask_oauth/oauth.py
google_flask_oauth-0.0.1.dev32.dist-info/METADATA
google_flask_oauth-0.0.1.dev32.dist-info/WHEEL
google_flask_oauth-0.0.1.dev32.dist-info/top_level.txt
google_flask_oauth-0.0.1.dev32.dist-info/RECORD
